viewpass
