Metadata-Version: 1.1
Name: django-viewpass
Version: 1.0.3
Summary: A Django app to provide access to protected resources via URL tokens.
Home-page: https://github.com/joelburton/viewpass.git
Author: Joel Burton
Author-email: joel@joelburton.com
License: GPL
Download-URL: https://github.com/joelburton/django-viewpass/tarball/1.0.3
Platform: UNKNOWN
Classifier: Environment :: Web Environment
Classifier: Framework :: Django
Classifier: Intended Audience :: Developers
Classifier: License :: OSI Approved :: GNU General Public License v3 or later (GPLv3+)
Classifier: Operating System :: OS Independent
Classifier: Programming Language :: Python
Classifier: Programming Language :: Python :: 2
Classifier: Programming Language :: Python :: 2.7
Classifier: Programming Language :: Python :: 3
Classifier: Programming Language :: Python :: 3.3
Classifier: Programming Language :: Python :: 3.4
Classifier: Programming Language :: Python :: 3.5
Classifier: Topic :: Internet :: WWW/HTTP
Classifier: Topic :: Internet :: WWW/HTTP :: Dynamic Content
